OBB/__init__.py
OBB/api.py
OBB/utils.py
OBB/shelf/__init__.py
OBB_Maya-0.1.15.dist-info/DESCRIPTION.rst
OBB_Maya-0.1.15.dist-info/METADATA
OBB_Maya-0.1.15.dist-info/RECORD
OBB_Maya-0.1.15.dist-info/WHEEL
OBB_Maya-0.1.15.dist-info/metadata.json
OBB_Maya-0.1.15.dist-info/top_level.txt
