Metadata-Version: 2.0
Name: OBB-Maya
Version: 0.1.15
Summary: Oriented Bounding Boxes in Maya.
Home-page: https://github.com/chrisdevito/OBB
Author: Christopher DeVito
Author-email: chrisdevito@chribis.com
License: MIT
Keywords: OBB
Platform: UNKNOWN
Classifier: Development Status :: 2 - Pre-Alpha
Classifier: Intended Audience :: Developers
Classifier: License :: OSI Approved :: MIT License
Classifier: Natural Language :: English
Classifier: Programming Language :: Python :: 2.7
